sam/__init__.py
sam/data_sources/__init__.py
sam/data_sources/mongo_wrapper.py
sam/data_sources/synthetic_data.py
sam/data_sources/weather/__init__.py
sam/data_sources/weather/knmi.py
sam/data_sources/weather/openweathermap.py
sam/data_sources/weather/regenradar.py
sam/data_sources/weather/utils.py
sam/datasets/__init__.py
sam/datasets/datasets.py
sam/datasets/data/rainbow_beach.csv
sam/datasets/data/sewage_data.csv
sam/exploration/__init__.py
sam/exploration/find_incidents.py
sam/exploration/lag_correlation.py
sam/exploration/top_correlation.py
sam/feature_engineering/__init__.py
sam/feature_engineering/automatic_rolling_engineering.py
sam/feature_engineering/base_feature_engineering.py
sam/feature_engineering/decompose_datetime.py
sam/feature_engineering/lag_range.py
sam/feature_engineering/rolling_features.py
sam/feature_engineering/simple_feature_engineering.py
sam/feature_engineering/weather_spei.py
sam/logging_functions/__init__.py
sam/logging_functions/dataframe_characteristics.py
sam/logging_functions/new_columns.py
sam/metrics/__init__.py
sam/metrics/custom_callbacks.py
sam/metrics/incident_recall.py
sam/metrics/keras_metrics.py
sam/metrics/mase.py
sam/metrics/quantile_evaluation.py
sam/metrics/r2_calculation.py
sam/metrics/tilted_loss_metrics.py
sam/models/__init__.py
sam/models/base_model.py
sam/models/benchmark.py
sam/models/constant_model.py
sam/models/keras_templates.py
sam/models/lasso_model.py
sam/models/linear_model.py
sam/models/mlp_model.py
sam/models/sam_shap_explainer.py
sam/models/utils.py
sam/preprocessing/__init__.py
sam/preprocessing/clip_transformer.py
sam/preprocessing/correct_extremes.py
sam/preprocessing/data_scaling.py
sam/preprocessing/differencing.py
sam/preprocessing/normalize_timestamps.py
sam/preprocessing/rnn_reshape.py
sam/preprocessing/sam_reshape.py
sam/preprocessing/time.py
sam/preprocessing/train_test_split.py
sam/utils/__init__.py
sam/utils/dataframe_functions.py
sam/utils/json_helpers.py
sam/utils/score_importance.py
sam-5.1.0.dist-info/licenses/LICENSE
sam-5.1.0.dist-info/METADATA
sam-5.1.0.dist-info/WHEEL
sam-5.1.0.dist-info/top_level.txt
sam-5.1.0.dist-info/RECORD
