Metadata-Version: 2.4
Name: sam
Version: 5.1.0
Summary: Time series anomaly detection and forecasting
Author-email: Royal HaskoningDHV <ruben.peters@rhdhv.com>
License: MIT
Project-URL: homepage, https://github.com/RoyalHaskoningDHV/sam
Project-URL: issues, https://github.com/RoyalHaskoningDHV/sam/issues
Project-URL: discussions, https://github.com/RoyalHaskoningDHV/sam/discussions
Project-URL: documentation, https://sam-rhdhv.readthedocs.io/en/latest/
Keywords: python,data-science,time-series,forecasting,anomaly-detection,asset-management
Classifier: Programming Language :: Python :: 3
Classifier: License :: OSI Approved :: MIT License
Classifier: Operating System :: OS Independent
Requires-Python: >=3.9
License-File: LICENSE
Requires-Dist: pandas~=2.2
Requires-Dist: numpy~=1.26
Requires-Dist: scikit-learn~=1.5.2
Provides-Extra: all
Requires-Dist: matplotlib; extra == "all"
Requires-Dist: cloudpickle; extra == "all"
Requires-Dist: nfft; extra == "all"
Requires-Dist: pymongo; extra == "all"
Requires-Dist: requests; extra == "all"
Requires-Dist: scipy~=1.13.1; extra == "all"
Requires-Dist: seaborn; extra == "all"
Requires-Dist: tensorflow<3,~=2.17; extra == "all"
Requires-Dist: Jinja2~=3.0.3; extra == "all"
Requires-Dist: onnx~=1.16.1; extra == "all"
Requires-Dist: onnxruntime~=1.19.2; extra == "all"
Requires-Dist: tf2onnx~=1.16.1; extra == "all"
Requires-Dist: shap; extra == "all"
Requires-Dist: plotly; extra == "all"
Requires-Dist: statsmodels; extra == "all"
Provides-Extra: plotting
Requires-Dist: matplotlib; extra == "plotting"
Requires-Dist: plotly; extra == "plotting"
Requires-Dist: seaborn; extra == "plotting"
Provides-Extra: data-engineering
Requires-Dist: requests; extra == "data-engineering"
Requires-Dist: pymongo; extra == "data-engineering"
Provides-Extra: data-science
Requires-Dist: tensorflow<3,~=2.17; extra == "data-science"
Requires-Dist: cloudpickle; extra == "data-science"
Requires-Dist: onnx~=1.16.1; extra == "data-science"
Requires-Dist: onnxruntime~=1.19.2; extra == "data-science"
Requires-Dist: tf2onnx~=1.16.1; extra == "data-science"
Requires-Dist: nfft; extra == "data-science"
Requires-Dist: scipy~=1.13.1; extra == "data-science"
Requires-Dist: shap; extra == "data-science"
Requires-Dist: Jinja2~=3.0.3; extra == "data-science"
Requires-Dist: statsmodels; extra == "data-science"
Provides-Extra: test
Requires-Dist: pytest; extra == "test"
Requires-Dist: pytest-cov; extra == "test"
Requires-Dist: pytest-mpl<=0.15.0; extra == "test"
Requires-Dist: fastparquet; extra == "test"
Provides-Extra: docs
Requires-Dist: sphinx; extra == "docs"
Requires-Dist: sphinx_rtd_theme; extra == "docs"
Requires-Dist: numpydoc; extra == "docs"
Requires-Dist: recommonmark; extra == "docs"
Requires-Dist: readthedocs-sphinx-search; extra == "docs"
Requires-Dist: sphinx-markdown-tables; extra == "docs"
Requires-Dist: toml; extra == "docs"
Requires-Dist: tensorflow<3,~=2.17; extra == "docs"
Dynamic: license-file
